[
  {
    "data_source": "aggregate_payload",
    "name": "ablation_comparison",
    "note": "正式论文优先引用 SVG；PNG 为 placeholder preview。",
    "path": "artifacts/phase12_2_clean/validation/plots/svg/ablation_comparison.svg",
    "type": "svg"
  },
  {
    "data_source": "aggregate_payload",
    "name": "backend_delta_distribution",
    "note": "正式论文优先引用 SVG；PNG 为 placeholder preview。",
    "path": "artifacts/phase12_2_clean/validation/plots/svg/backend_delta_distribution.svg",
    "type": "svg"
  },
  {
    "data_source": "aggregate_payload",
    "name": "cloud_invocation_bar",
    "note": "正式论文优先引用 SVG；PNG 为 placeholder preview。",
    "path": "artifacts/phase12_2_clean/validation/plots/svg/cloud_invocation_bar.svg",
    "type": "svg"
  },
  {
    "data_source": "aggregate_payload",
    "name": "communication_count_bar",
    "note": "正式论文优先引用 SVG；PNG 为 placeholder preview。",
    "path": "artifacts/phase12_2_clean/validation/plots/svg/communication_count_bar.svg",
    "type": "svg"
  },
  {
    "data_source": "aggregate_payload",
    "name": "completion_time_box",
    "note": "正式论文优先引用 SVG；PNG 为 placeholder preview。",
    "path": "artifacts/phase12_2_clean/validation/plots/svg/completion_time_box.svg",
    "type": "svg"
  },
  {
    "data_source": "aggregate_payload",
    "name": "failure_composition",
    "note": "正式论文优先引用 SVG；PNG 为 placeholder preview。",
    "path": "artifacts/phase12_2_clean/validation/plots/svg/failure_composition.svg",
    "type": "svg"
  },
  {
    "data_source": "aggregate_payload",
    "name": "local_recovery_effect",
    "note": "正式论文优先引用 SVG；PNG 为 placeholder preview。",
    "path": "artifacts/phase12_2_clean/validation/plots/svg/local_recovery_effect.svg",
    "type": "svg"
  },
  {
    "data_source": "aggregate_payload",
    "name": "mode_overall_comparison",
    "note": "正式论文优先引用 SVG；PNG 为 placeholder preview。",
    "path": "artifacts/phase12_2_clean/validation/plots/svg/mode_overall_comparison.svg",
    "type": "svg"
  },
  {
    "data_source": "aggregate_payload",
    "name": "mujoco_isaac_paired_scatter",
    "note": "正式论文优先引用 SVG；PNG 为 placeholder preview。",
    "path": "artifacts/phase12_2_clean/validation/plots/svg/mujoco_isaac_paired_scatter.svg",
    "type": "svg"
  },
  {
    "data_source": "aggregate_payload",
    "name": "network_latency_sensitivity",
    "note": "正式论文优先引用 SVG；PNG 为 placeholder preview。",
    "path": "artifacts/phase12_2_clean/validation/plots/svg/network_latency_sensitivity.svg",
    "type": "svg"
  },
  {
    "data_source": "aggregate_payload",
    "name": "packet_loss_sensitivity",
    "note": "正式论文优先引用 SVG；PNG 为 placeholder preview。",
    "path": "artifacts/phase12_2_clean/validation/plots/svg/packet_loss_sensitivity.svg",
    "type": "svg"
  },
  {
    "data_source": "aggregate_payload",
    "name": "planner_latency",
    "note": "正式论文优先引用 SVG；PNG 为 placeholder preview。",
    "path": "artifacts/phase12_2_clean/validation/plots/svg/planner_latency.svg",
    "type": "svg"
  },
  {
    "data_source": "aggregate_payload",
    "name": "planner_valid_contract_rate",
    "note": "正式论文优先引用 SVG；PNG 为 placeholder preview。",
    "path": "artifacts/phase12_2_clean/validation/plots/svg/planner_valid_contract_rate.svg",
    "type": "svg"
  },
  {
    "data_source": "aggregate_payload",
    "name": "replanning_count_comparison",
    "note": "正式论文优先引用 SVG；PNG 为 placeholder preview。",
    "path": "artifacts/phase12_2_clean/validation/plots/svg/replanning_count_comparison.svg",
    "type": "svg"
  },
  {
    "data_source": "aggregate_payload",
    "name": "safety_intervention_count",
    "note": "正式论文优先引用 SVG；PNG 为 placeholder preview。",
    "path": "artifacts/phase12_2_clean/validation/plots/svg/safety_intervention_count.svg",
    "type": "svg"
  },
  {
    "data_source": "aggregate_payload",
    "name": "stress_recovery_timeline",
    "note": "正式论文优先引用 SVG；PNG 为 placeholder preview。",
    "path": "artifacts/phase12_2_clean/validation/plots/svg/stress_recovery_timeline.svg",
    "type": "svg"
  },
  {
    "data_source": "aggregate_payload",
    "name": "success_rate_comparison",
    "note": "正式论文优先引用 SVG；PNG 为 placeholder preview。",
    "path": "artifacts/phase12_2_clean/validation/plots/svg/success_rate_comparison.svg",
    "type": "svg"
  }
]
